quickparser/__init__.py
quickparser/parser_tools.py
quickparser-0.1.2.dist-info/METADATA
quickparser-0.1.2.dist-info/WHEEL
quickparser-0.1.2.dist-info/top_level.txt
quickparser-0.1.2.dist-info/RECORD
